hvpdb_query/__init__.py
hvpdb_query/cli.py
hvpdb_query/engine.py
hvpdb_query/parser.py
hvpdb_query-0.1.0.dist-info/METADATA
hvpdb_query-0.1.0.dist-info/WHEEL
hvpdb_query-0.1.0.dist-info/entry_points.txt
hvpdb_query-0.1.0.dist-info/top_level.txt
hvpdb_query-0.1.0.dist-info/RECORD
