Metadata-Version: 2.4
Name: hvpdb-query
Version: 0.1.0
Summary: Polyglot Query Plugin for HVPDB (SQL, Mongo, Redis)
Author: HVPDB Team
Classifier: Programming Language :: Python :: 3
Classifier: License :: OSI Approved :: MIT License
Classifier: Operating System :: OS Independent
Requires-Python: >=3.6
Dynamic: author
Dynamic: classifier
Dynamic: requires-python
Dynamic: summary
